skutter/__init__.py
skutter/configuration.py
skutter/jobmanager.py
skutter/skutterd.py
skutter/actions/__init__.py
skutter/actions/actions.py
skutter/actions/exec.py
skutter/actions/firewalld.py
skutter/actions/iptables.py
skutter/actions/nftables.py
skutter/actions/toml.py
skutter/actions/yaml.py
skutter/checks/__init__.py
skutter/checks/process.py
skutter/tests/__init__.py
skutter-0.11.data/scripts/skutter
skutter-0.11.dist-info/LICENSE.md
skutter-0.11.dist-info/METADATA
skutter-0.11.dist-info/WHEEL
skutter-0.11.dist-info/entry_points.txt
skutter-0.11.dist-info/top_level.txt
skutter-0.11.dist-info/RECORD
