Metadata-Version: 2.1
Name: skutter
Version: 0.11
Summary: Skutter is a daemon for executing menial tasks.
Home-page: https://github.com/TheMysteriousX/skutter
Author: Adam Bishop
Author-email: adam@omega.org.uk
License: GNU GPL v3
Platform: UNKNOWN
Classifier: Development Status :: 4 - Beta
Classifier: License :: OSI Approved :: GNU General Public License v3 (GPLv3)
Classifier: Programming Language :: Python :: 3.7
Requires-Dist: pbr
Requires-Dist: psutil
Requires-Dist: python-iptables
Requires-Dist: PyYAML
Requires-Dist: six
Requires-Dist: stevedore
